SimrightCsrf
