Metadata-Version: 1.1
Name: simright-csrf
Version: 0.0.4
Summary: www.simright.com csrf token
Home-page: UNKNOWN
Author: <yangjiaronga>
Author-email: <yangjiaronga@gmail.com>
License: MIT License
Platform: all
Classifier: Programming Language :: Python
Classifier: Programming Language :: Python :: Implementation
Classifier: Programming Language :: Python :: 2
Classifier: Programming Language :: Python :: 2.7
Classifier: Programming Language :: Python :: 3
Classifier: Programming Language :: Python :: 3.4
Classifier: Programming Language :: Python :: 3.5
Classifier: Programming Language :: Python :: 3.6
